xmlformatter.py
xmlformatter-0.2.8.dist-info/LICENSE.txt
xmlformatter-0.2.8.dist-info/METADATA
xmlformatter-0.2.8.dist-info/WHEEL
xmlformatter-0.2.8.dist-info/entry_points.txt
xmlformatter-0.2.8.dist-info/top_level.txt
xmlformatter-0.2.8.dist-info/RECORD
