Metadata-Version: 2.1
Name: xmlformatter
Version: 0.2.8
Summary: Format and compress XML documents
Home-page: http://pamoller.com/xmlformatter.html
Author: P. Andreas Moeller
Author-email: kontakt@pamoller.com
License: MIT
Classifier: Programming Language :: Python :: 2
Classifier: Programming Language :: Python :: 2.6
Classifier: Programming Language :: Python :: 2.7
Classifier: Programming Language :: Python :: 3
Classifier: Programming Language :: Python :: 3.2
Classifier: License :: OSI Approved :: MIT License
Classifier: Topic :: Text Processing :: Markup :: XML
License-File: LICENSE.txt
